agent_memory_jojo/__init__.py
agent_memory_jojo/agents/__init__.py
agent_memory_jojo/agents/agent.py
agent_memory_jojo/agents/base_agent.py
agent_memory_jojo/agents/prompt/templates/fact_retrieval_system_prompt.txt
agent_memory_jojo/agents/prompt/templates/fact_system_prompt.txt
agent_memory_jojo/client/__init__.py
agent_memory_jojo/client/qdrant_client.py
agent_memory_jojo/config/__init__.py
agent_memory_jojo/config/app_config.yml
agent_memory_jojo/config/config_helper.py
agent_memory_jojo/config/logger.py
agent_memory_jojo/custom/__init__.py
agent_memory_jojo/custom/documents.py
agent_memory_jojo/processors/__init__.py
agent_memory_jojo/processors/intelligent.py
agent_memory_jojo/schema/__init__.py
agent_memory_jojo/schema/document_schema.py
agent_memory_jojo/schema/fact_schema.py
agent_memory_jojo/schema/search_schema.py
agent_memory_jojo/utils/__init__.py
agent_memory_jojo/utils/app_utils.py
agent_memory_jojo-0.1.3.dist-info/METADATA
agent_memory_jojo-0.1.3.dist-info/WHEEL
agent_memory_jojo-0.1.3.dist-info/RECORD
