Metadata-Version: 2.1
Name: agent_memory_jojo
Version: 0.1.3
Summary: 
Author: danielAdama
Author-email: adamadaniel321@gmail.com
Requires-Python: >=3.11,<4.0
Classifier: Programming Language :: Python :: 3
Classifier: Programming Language :: Python :: 3.11
Classifier: Programming Language :: Python :: 3.12
Classifier: Programming Language :: Python :: 3.13
Requires-Dist: huggingface-hub (>=0.28.1,<0.29.0)
Requires-Dist: langchain-community (>=0.3.17rc1,<0.4.0)
Requires-Dist: langchain-groq (>=0.2.4,<0.3.0)
Requires-Dist: langchain-openai (>=0.3.4,<0.4.0)
Requires-Dist: langgraph (>=0.2.69,<0.3.0)
Requires-Dist: numpy (==1.26.4)
Requires-Dist: openai (>=1.63.0,<2.0.0)
Requires-Dist: python-dotenv (>=1.0.1,<2.0.0)
Requires-Dist: qdrant-client (>=1.12.1,<2.0.0)
Requires-Dist: sentence-transformers (>=3.4.1,<4.0.0)
Requires-Dist: tenacity (>=9.0.0,<10.0.0)
Requires-Dist: tokenizers (>=0.21.0,<0.22.0)
Requires-Dist: tqdm (>=4.67.1,<5.0.0)
